[{"songId":690,"songName":"下个, 路口, 见","singerId":152,"singerName":"李宇春","playCount":1,"type":"flac","src":"1.flac","lrc":"1.lrc","tags":[]},{"songId":691,"songName":"再不疯狂我们就老了","singerId":152,"singerName":"李宇春","playCount":1,"type":"flac","src":"2.flac","lrc":"2.lrc","tags":[]},{"songId":692,"songName":"刀锋偏冷","singerId":152,"singerName":"李宇春","playCount":1,"type":"flac","src":"3.flac","lrc":"3.lrc","tags":[]},{"songId":693,"songName":"千年游","singerId":152,"singerName":"李宇春","playCount":1,"type":"flac","src":"4.flac","lrc":"4.lrc","tags":[]},{"songId":694,"songName":"和你一样","singerId":152,"singerName":"李宇春","playCount":1,"type":"flac","src":"5.flac","lrc":"5.lrc","tags":[]},{"songId":695,"songName":"蜀绣","singerId":152,"singerName":"李宇春","playCount":1,"type":"flac","src":"6.flac","lrc":"6.lrc","tags":[]},{"songId":696,"songName":"银河中的星星","singerId":152,"singerName":"李宇春","playCount":1,"type":"flac","src":"7.flac","lrc":"7.lrc","tags":[]}]