[{"songId":701,"songName":"一笑而过","singerId":155,"singerName":"那英","playCount":1,"type":"flac","src":"1.flac","lrc":"1.lrc","tags":[]},{"songId":702,"songName":"孤帆","singerId":155,"singerName":"那英","playCount":1,"type":"flac","src":"2.flac","lrc":"2.lrc","tags":[]},{"songId":703,"songName":"征服","singerId":155,"singerName":"那英","playCount":1,"type":"flac","src":"3.flac","lrc":"3.lrc","tags":[]},{"songId":704,"songName":"梦一场","singerId":155,"singerName":"那英","playCount":1,"type":"flac","src":"4.flac","lrc":"4.lrc","tags":[]},{"songId":705,"songName":"白天不懂夜的黑","singerId":155,"singerName":"那英","playCount":1,"type":"flac","src":"5.flac","lrc":"5.lrc","tags":[]},{"songId":706,"songName":"雾里看花","singerId":155,"singerName":"那英","playCount":1,"type":"flac","src":"6.flac","lrc":"6.lrc","tags":[]},{"songId":707,"songName":"默","singerId":155,"singerName":"那英","playCount":1,"type":"flac","src":"7.flac","lrc":"7.lrc","tags":[]}]